Metadata-Version: 1.0
Name: liplustools
Version: 0.2
Summary: move joke function into text.py 
Home-page: http://github.com/storborg/funniest
Author: liplus
Author-email: liplus@example.com
License: MIT
Platform: UNKNOWN
